visioncar_polygon_control/__init__.py
visioncar_polygon_control/__main__.py
visioncar_polygon_control/colorselect.py
visioncar_polygon_control/decorators.py
visioncar_polygon_control/device.py
visioncar_polygon_control/main.py
visioncar_polygon_control/profile.py
visioncar_polygon_control/startpage.py
visioncar_polygon_control-0.1.10.dist-info/LICENSE
visioncar_polygon_control-0.1.10.dist-info/METADATA
visioncar_polygon_control-0.1.10.dist-info/WHEEL
visioncar_polygon_control-0.1.10.dist-info/entry_points.txt
visioncar_polygon_control-0.1.10.dist-info/top_level.txt
visioncar_polygon_control-0.1.10.dist-info/RECORD
