Metadata-Version: 2.1
Name: visioncar-polygon-control
Version: 0.1.10
Summary: PySide6 application for controlling polygon elements
Author: VisionCar team
Classifier: Development Status :: 5 - Production/Stable
Classifier: License :: OSI Approved :: GNU Lesser General Public License v3 (LGPLv3)
Classifier: Operating System :: OS Independent
Requires-Python: >=3.10
License-File: LICENSE
Requires-Dist: PySide6 ==6.6.*
Requires-Dist: qt-material ==2.*
Requires-Dist: requests ==2.31.*
Requires-Dist: zeroconf
Requires-Dist: QtAwesome ==1.2.*
